nos_parser/GCS_persistence.py
nos_parser/__init__.py
nos_parser/drain.py
nos_parser/file_persistence.py
nos_parser/masking.py
nos_parser/memory_buffer_persistence.py
nos_parser/persistence_handler.py
nos_parser/simple_profiler.py
nos_parser/template_miner.py
nos_parser/template_miner_config.py
Nosparser-0.11.dist-info/LICENSE.txt
Nosparser-0.11.dist-info/METADATA
Nosparser-0.11.dist-info/WHEEL
Nosparser-0.11.dist-info/top_level.txt
Nosparser-0.11.dist-info/RECORD
