Metadata-Version: 2.1
Name: Nosparser
Version: 0.11
Summary: Persistent & streaming log template miner
Home-page: UNKNOWN
License: MIT
Keywords: drain,log,parser,IBM,template,logs,miner
Platform: UNKNOWN
Classifier: Programming Language :: Python :: 3.6
Classifier: Programming Language :: Python :: 3.7
Classifier: License :: OSI Approved :: MIT License
Classifier: Operating System :: OS Independent
Classifier: Topic :: Software Development :: Libraries
Requires-Python: >=3.6
License-File: LICENSE.txt
Requires-Dist: jsonpickle (==1.5.1)
Requires-Dist: cachetools (==4.2.1)
